{
  "date": "2025-07-28",
  "source": "blognone",
  "articles": [
    {
      "id": "147552 at https://www.blognone.com",
      "title": "ข้อมูลช่องโหว่ SharePoint อาจรั่วไหลจากพาร์ทเนอร์ไมโครซอฟท์ที่รู้ข้อมูลล่วงหน้า",
      "description": "ข้อมูลช่องโหว่ SharePoint อาจรั่วไหลจากพาร์ทเนอร์ไมโครซอฟท์ที่รู้ข้อมูลล่วงหน้า Body จาก กรณีช่องโหว่ SharePoint รอบล่าสุดที่ถูกใช้โจมตีจริง และ",
      "url": "https://www.blognone.com/node/147552",
      "publishedAt": "2025-07-28T01:17:49.000Z",
      "source": "blognone",
      "sourceName": "Blognone",
      "author": "Blognone",
      "tags": []
    }
  ]
}