{
  "date": "2025-12-29",
  "source": "blognone",
  "articles": [
    {
      "id": "149317 at https://www.blognone.com",
      "title": "NT เดินหน้ายกระดับความมั่นคงปลอดภัยทางไซเบอร์ของประเทศ เปิดศูนย์ “CyberXpert Center” สร้างบุคลากรคุณภาพพร้อมรับมือภัยคุกคามยุคดิจิทัล",
      "description": "NT เดินหน้ายกระดับความมั่นคงปลอดภัยทางไซเบอร์ของประเทศ เปิดศูนย์ “CyberXpert Center” สร้างบุคลากรคุณภาพพร้อมรับมือภัยคุกคามยุคดิจิทัล Body กรุงเทพฯ –",
      "url": "https://www.blognone.com/node/149317",
      "imageUrl": "https://www.blognone.com/sites/default/files/files-2025/2025-12/NT/01_0.jpg",
      "publishedAt": "2025-12-29T04:30:00.000Z",
      "source": "blognone",
      "sourceName": "Blognone",
      "author": "Blognone",
      "tags": []
    }
  ]
}