{
  "date": "2025-07-16",
  "source": "blognone",
  "articles": [
    {
      "id": "147419 at https://www.blognone.com",
      "title": "Roblox เปิดตัว License Manager ให้เจ้าของแฟรนไชส์เชื่อมครีเอเตอร์ อนุญาตใช้งานตัวละคร",
      "description": "Roblox เปิดตัว License Manager ให้เจ้าของแฟรนไชส์เชื่อมครีเอเตอร์ อนุญาตใช้งานตัวละคร Body จักรวาล Roblox",
      "url": "https://www.blognone.com/node/147419",
      "publishedAt": "2025-07-16T01:56:55.000Z",
      "source": "blognone",
      "sourceName": "Blognone",
      "author": "Blognone",
      "tags": []
    },
    {
      "id": "147418 at https://www.blognone.com",
      "title": "Cyberpunk 2077: Ultimate Edition ประกาศขายเวอร์ชัน Mac วันที่ 17 ก.ค. 2025",
      "description": "Cyberpunk 2077: Ultimate Edition ประกาศขายเวอร์ชัน Mac วันที่ 17 ก.ค. 2025 Body เกมมหาชน Cyberpunk 2077 เดินทางมาถึงแพลตฟอร์ม (น่าจะท้ายๆ) คือ macOS",
      "url": "https://www.blognone.com/node/147418",
      "publishedAt": "2025-07-16T01:41:25.000Z",
      "source": "blognone",
      "sourceName": "Blognone",
      "author": "Blognone",
      "tags": []
    },
    {
      "id": "147417 at https://www.blognone.com",
      "title": "Mistral เปิดตัว Voxtrol โมเดล AI สำหรับเสียงแบบโอเพนซอร์ส ที่ทำงานได้ดีด้วยต้นทุนที่ถูกกว่าคู่แข่ง",
      "description": "Mistral เปิดตัว Voxtrol โมเดล AI สำหรับเสียงแบบโอเพนซอร์ส ที่ทำงานได้ดีด้วยต้นทุนที่ถูกกว่าคู่แข่ง Body Mistral AI เปิดตัว Voxtral โมเดล AI",
      "url": "https://www.blognone.com/node/147417",
      "publishedAt": "2025-07-16T01:02:19.000Z",
      "source": "blognone",
      "sourceName": "Blognone",
      "author": "Blognone",
      "tags": []
    },
    {
      "id": "147416 at https://www.blognone.com",
      "title": "Google ซื้อไฟฟ้าพลังน้ำระยะเวลา 20 ปี 670 เมกะวัตต์ มูลค่าสัญญา 3 พันล้านดอลลาร์",
      "description": "Google ซื้อไฟฟ้าพลังน้ำระยะเวลา 20 ปี 670 เมกะวัตต์ มูลค่าสัญญา 3 พันล้านดอลลาร์ Body ประเด็นการขยายโครงสร้างพื้นฐาน AI",
      "url": "https://www.blognone.com/node/147416",
      "publishedAt": "2025-07-16T00:33:15.000Z",
      "source": "blognone",
      "sourceName": "Blognone",
      "author": "Blognone",
      "tags": []
    },
    {
      "id": "147415 at https://www.blognone.com",
      "title": "Thinking Machines Lab รับเงินลงทุน 2,000 ล้านดอลลาร์ ในรอบ Seeding จาก NVIDIA, AMD",
      "description": "Thinking Machines Lab รับเงินลงทุน 2,000 ล้านดอลลาร์ ในรอบ Seeding จาก NVIDIA, AMD Body Thinking Machines Lab สตาร์ทอัปปัญญาประดิษฐ์ที่ ก่อตั้งโดย",
      "url": "https://www.blognone.com/node/147415",
      "publishedAt": "2025-07-16T00:17:27.000Z",
      "source": "blognone",
      "sourceName": "Blognone",
      "author": "Blognone",
      "tags": []
    }
  ]
}