{
  "date": "2026-02-09",
  "source": "blognone",
  "articles": [
    {
      "id": "149681 at https://www.blognone.com",
      "title": "ผู้สร้าง Ghostty เริ่มใช้ระบบคะแนนความน่าเชื่อถือ ก่อนรับโค้ดจากภายนอก",
      "description": "ผู้สร้าง Ghostty เริ่มใช้ระบบคะแนนความน่าเชื่อถือ ก่อนรับโค้ดจากภายนอก Body Mitchell Hashimoto ผู้สร้างโปรแกรม Ghostty ที่เป็น terminal emulator",
      "url": "https://www.blognone.com/node/149681",
      "publishedAt": "2026-02-09T06:05:23.000Z",
      "source": "blognone",
      "sourceName": "Blognone",
      "author": "Blognone",
      "tags": []
    }
  ]
}