{
  "date": "2025-09-21",
  "source": "techcrunch",
  "articles": [
    {
      "id": "https://techcrunch.com/?p=3048328",
      "title": "VCs are still hiring MBAs, but firms are starting to need other experience more",
      "description": "The MBA-to-VC pipeline remains a very real thing. But that path is a little shakier than it once was, according to PitchBook reporting and new",
      "url": "https://techcrunch.com/2025/09/21/vcs-are-still-hiring-mbas-but-firms-are-starting-to-need-other-experience-more/",
      "publishedAt": "2025-09-21T22:23:40.000Z",
      "source": "techcrunch",
      "sourceName": "TechCrunch",
      "author": "Connie Loizos",
      "tags": []
    },
    {
      "id": "https://techcrunch.com/?p=3048222",
      "title": "Trump says Lachlan and Rupert Murdoch might invest in TikTok deal",
      "description": "The Trump administration has been talking up a potential TikTok deal this weekend, with President Donald Trump telling Fox News on Sunday that Rupert",
      "url": "https://techcrunch.com/2025/09/21/white-house-offers-more-details-about-potential-tiktok-deal/",
      "publishedAt": "2025-09-21T19:43:34.000Z",
      "source": "techcrunch",
      "sourceName": "TechCrunch",
      "author": "Anthony Ha",
      "tags": []
    },
    {
      "id": "https://techcrunch.com/?p=3040939",
      "title": "Silicon Valley bets big on ‘environments’ to train AI agents",
      "description": "A wave of startups are creating RL environments to help AI labs train agents. It might be Silicon Valley’s next craze in the making.",
      "url": "https://techcrunch.com/2025/09/21/silicon-valley-bets-big-on-environments-to-train-ai-agents/",
      "publishedAt": "2025-09-21T19:22:56.000Z",
      "source": "techcrunch",
      "sourceName": "TechCrunch",
      "author": "Maxwell Zeff",
      "tags": []
    },
    {
      "id": "https://techcrunch.com/?p=3047892",
      "title": "TechCrunch Mobility: The two robotaxi battlegrounds that matter",
      "description": "Welcome back to TechCrunch Mobility, your hub for all things “future of transportation.”",
      "url": "https://techcrunch.com/2025/09/21/techcrunch-mobility-the-two-robotaxi-battlegrounds-that-matter/",
      "publishedAt": "2025-09-21T16:01:00.000Z",
      "source": "techcrunch",
      "sourceName": "TechCrunch",
      "author": "Kirsten Korosec",
      "tags": []
    },
    {
      "id": "https://techcrunch.com/?p=3048311",
      "title": "Hundreds of flights delayed at Heathrow and other airports after apparent cyberattack",
      "description": "Travelers at major European airports including Heathrow, Brussels, and Berlin faced significant delays this weekend following what Collins Aerospace",
      "url": "https://techcrunch.com/2025/09/21/hundreds-of-flights-delayed-at-heathrow-and-other-airports-after-apparent-cyberattack/",
      "publishedAt": "2025-09-21T15:03:26.000Z",
      "source": "techcrunch",
      "sourceName": "TechCrunch",
      "author": "Anthony Ha",
      "tags": []
    },
    {
      "id": "https://techcrunch.com/?p=3048211",
      "title": "Amazon, Google, Microsoft reportedly warn H-1B employees to stay in the US",
      "description": "Large tech companies have responded to President Donald Trump’s dramatic changes to H-1B visa applications by telling employees with those visas to",
      "url": "https://techcrunch.com/2025/09/21/amazon-google-microsoft-warn-h-1b-employees-to-stay-in-the-us/",
      "publishedAt": "2025-09-21T14:09:00.000Z",
      "source": "techcrunch",
      "sourceName": "TechCrunch",
      "author": "Anthony Ha",
      "tags": []
    },
    {
      "id": "https://techcrunch.com/?p=3046951",
      "title": "6 days left: Last chance for Regular Bird savings for TechCrunch Disrupt 2025 passes",
      "description": "Time’s ticking! Register by September 26 at 11:59 p.m. PT to lock in Regular-Bird pricing and save up to $668 on your pass to TechCrunch Disrupt",
      "url": "https://techcrunch.com/2025/09/21/6-days-left-last-chance-for-regular-bird-pricing/",
      "publishedAt": "2025-09-21T14:00:00.000Z",
      "source": "techcrunch",
      "sourceName": "TechCrunch",
      "author": "TechCrunch Events",
      "tags": []
    }
  ]
}