{
  "date": "2025-08-30",
  "source": "techcrunch",
  "articles": [
    {
      "id": "https://techcrunch.com/?p=3040988",
      "title": "Cracks are forming in Meta’s partnership with Scale AI",
      "description": "Two months after making a $14.3B investment in Scale AI, Meta is relying heavily on its competitors to train next generation AI models.",
      "url": "https://techcrunch.com/2025/08/29/cracks-are-forming-in-metas-partnership-with-scale-ai/",
      "publishedAt": "2025-08-30T01:34:05.000Z",
      "source": "techcrunch",
      "sourceName": "TechCrunch",
      "author": "Maxwell Zeff, Marina Temkin",
      "tags": []
    }
  ]
}