{
  "date": "2026-04-22",
  "source": "techcrunch",
  "articles": [
    {
      "id": "https://techcrunch.com/?p=3114892",
      "title": "Redwood Materials lays off 10% in restructuring to chase energy storage business",
      "description": "The company is restructuring some teams to accommodate a booming energy storage business, according to emails viewed by TechCrunch.",
      "url": "https://techcrunch.com/2026/04/21/redwood-materials-lays-off-10-in-restructuring-to-chase-energy-storage-business/",
      "publishedAt": "2026-04-22T00:37:33.000Z",
      "source": "techcrunch",
      "sourceName": "TechCrunch",
      "author": "Sean O'Kane",
      "tags": []
    }
  ]
}