{
  "date": "2025-09-26",
  "source": "theverge",
  "articles": [
    {
      "id": "79dauq",
      "title": "Microsoft and Asus open Xbox Ally preorders — the X costs $999",
      "description": "Today, Microsoft and Asus are officially opening preorders for the ROG Xbox Ally and ROG Xbox Ally X at $599 and $999 respectively in the US. They’re $799 CAD and $1299 CAD in Canada, €599 and €899 in Europe, £499 and £799 in the UK, and $799 AUD and $1599 AUD in Australia. They both [&#8230;]",
      "url": "https://www.theverge.com/news/784286/xbox-handheld-ally-x-price-preorder",
      "imageUrl": "https://platform.theverge.com/wp-content/uploads/sites/2/2025/09/VLS_5799-copy.jpg?quality=90&#038;strip=all&#038;crop=0,0,100,100",
      "publishedAt": "2025-09-26T00:00:00.000Z",
      "source": "theverge",
      "sourceName": "The Verge",
      "author": "Sean Hollister",
      "tags": []
    }
  ]
}