{
  "date": "2025-08-20",
  "source": "theverge",
  "articles": [
    {
      "id": "6veo96",
      "title": "The White House just joined TikTok",
      "description": "While it was President Joe Biden who signed the law that would force  ByteDance to sell its stake in TikTok or face a ban, it’s his successor, Donald Trump, who has yet to fulfill his promise of arranging a deal to keep TikTok running, legally, in the United States. The current deadline for a deal [&#8230;]",
      "url": "https://www.theverge.com/politics/762031/trump-white-house-tiktok-account",
      "imageUrl": "https://platform.theverge.com/wp-content/uploads/sites/2/2025/02/STK175_DONALD_TRUMP_CVIRGINIA_C.jpg?quality=90&#038;strip=all&#038;crop=0,0,100,100",
      "publishedAt": "2025-08-20T01:21:13.000Z",
      "source": "theverge",
      "sourceName": "The Verge",
      "author": "Tina Nguyen",
      "tags": []
    }
  ]
}